LICENSE
MANIFEST.in
README.md
setup.py
tests.py
MarkovNetwork/MarkovNetwork.py
MarkovNetwork/__init__.py
MarkovNetwork/_version.py
MarkovNetwork.egg-info/PKG-INFO
MarkovNetwork.egg-info/SOURCES.txt
MarkovNetwork.egg-info/dependency_links.txt
MarkovNetwork.egg-info/requires.txt
MarkovNetwork.egg-info/top_level.txt
MarkovNetwork.egg-info/zip-safe